plaques/__init__.py
plaques/base.py
plaques/elements.py
plaques-0.9.dist-info/WHEEL
plaques-0.9.dist-info/METADATA
plaques-0.9.dist-info/RECORD
