Metadata-Version: 2.1
Name: plaques
Version: 0.9
Summary: A minimalistic TUI (Text User Interface) library for Linux.
Author-email: farlep <de.arapaima@gmail.com>
Requires-Dist: wcwidth
Project-URL: Home, https://github.com/farlep/plaques
